scssto/__init__.py
scssto/__main__.py
scssto/compiler.py
scssto-2.0.0.dist-info/METADATA
scssto-2.0.0.dist-info/WHEEL
scssto-2.0.0.dist-info/entry_points.txt
scssto-2.0.0.dist-info/top_level.txt
scssto-2.0.0.dist-info/RECORD
