Metadata-Version: 2.4
Name: scssto
Version: 2.0.0
Summary: Compile all .scss files from a folder into .css
Home-page: https://taplink.cc/qaxxorovc
Author: Axmadjon Qaxxorov
Author-email: qaxxorovc.work@gmail.com
Classifier: Programming Language :: Python :: 3
Classifier: License :: OSI Approved :: MIT License
Classifier: Operating System :: OS Independent
Requires-Python: >=3.6
Dynamic: author
Dynamic: author-email
Dynamic: classifier
Dynamic: description
Dynamic: description-content-type
Dynamic: home-page
Dynamic: requires-python
Dynamic: summary
